LICENSE
README.md
setup.py
cubo/__init__.py
cubo/cubo.py
cubo/utils.py
cubo.egg-info/PKG-INFO
cubo.egg-info/SOURCES.txt
cubo.egg-info/dependency_links.txt
cubo.egg-info/requires.txt
cubo.egg-info/top_level.txt
tests/test_cubo.py