Metadata-Version: 2.1
Name: cubo
Version: 2024.8.0
Summary: On-Demand Earth System Data Cubes in Python
Home-page: https://github.com/davemlz/cubo
Author: David Montero Loaiza
Author-email: dml.mont@gmail.com
License: MIT
Classifier: Development Status :: 2 - Pre-Alpha
Classifier: License :: OSI Approved :: MIT License
Classifier: Programming Language :: Python
Classifier: Programming Language :: Python :: 3
Classifier: Programming Language :: Python :: 3.7
Classifier: Programming Language :: Python :: 3.8
Classifier: Programming Language :: Python :: 3.9
Provides-Extra: ee
License-File: LICENSE
